pysyncasync/__init__.py
pysyncasync/call.py
pysyncasync/constants.py
pysyncasync/exceptions.py
pysyncasync/generator.py
pysyncasync/manager.py
pysyncasync/root.py
pysyncasync/tests/__init__.py
pysyncasync/tests/common.py
pysyncasync/tests/test_import.py
pysyncasync/tests/test_manager.py
pysyncasync/tests/test_root.py
pySyncAsync-1.0.0.dist-info/METADATA
pySyncAsync-1.0.0.dist-info/WHEEL
pySyncAsync-1.0.0.dist-info/top_level.txt
pySyncAsync-1.0.0.dist-info/RECORD
