Metadata-Version: 2.1
Name: pySyncAsync
Version: 1.0.0
Summary: UNKNOWN
Home-page: https://github.com/OlegYurchik/pySyncAsync
Author: Oleg Yurchik
Author-email: oleg.yurchik@protonmail.com
License: UNKNOWN
Platform: UNKNOWN
